remotedb/__init__.py
remotedb/client.py
remotedb/response.py
remotedb-1.0.0.dist-info/LICENSE
remotedb-1.0.0.dist-info/METADATA
remotedb-1.0.0.dist-info/WHEEL
remotedb-1.0.0.dist-info/top_level.txt
remotedb-1.0.0.dist-info/RECORD
