Metadata-Version: 2.1
Name: remotedb
Version: 1.0.0
Summary: Official Python API Wrapper for Hosting HQ RemoteDB
Home-page: https://github.com/Hosting-HQ/remotedb-py
Author: Hosting HQ LLC
Author-email: justyn@hostinghq.xyz
License: UNKNOWN
Project-URL: Bug Tracker, https://github.com/Hosting-HQ/remotedb-py/issues
Platform: UNKNOWN
Classifier: Programming Language :: Python :: 3
Classifier: License :: OSI Approved :: GNU General Public License v3 (GPLv3)
Classifier: Operating System :: OS Independent
Requires-Python: >=3.6
